.travis.yml
CHANGELOG.md
CONTRIBUTING.md
ISSUE_TEMPLATE.md
LICENSE-pwntools.txt
MANIFEST.in
PULL_REQUEST_TEMPLATE.md
README.md
TESTING.md
requirements.txt
setup.py
docs/Makefile
docs/dashbuild.py
docs/requirements.txt
docs/source/about.rst
docs/source/adb.rst
docs/source/asm.rst
docs/source/atexception.rst
docs/source/atexit.rst
docs/source/commandline.rst
docs/source/conf.py
docs/source/constants.rst
docs/source/context.rst
docs/source/dynelf.rst
docs/source/elf.rst
docs/source/encoders.rst
docs/source/exception.rst
docs/source/flag.rst
docs/source/fmtstr.rst
docs/source/gdb.rst
docs/source/globals.rst
docs/source/index.rst
docs/source/install.rst
docs/source/intro.rst
docs/source/log.rst
docs/source/logo.png
docs/source/memleak.rst
docs/source/replacements.rst
docs/source/rop.rst
docs/source/runner.rst
docs/source/shellcraft.rst
docs/source/term.rst
docs/source/testexample.rst
docs/source/timeout.rst
docs/source/tubes.rst
docs/source/ui.rst
docs/source/update.rst
docs/source/useragents.rst
docs/source/install/binutils.rst
docs/source/install/headers.rst
docs/source/rop/rop.rst
docs/source/rop/srop.rst
docs/source/shellcraft/amd64.rst
docs/source/shellcraft/arm.rst
docs/source/shellcraft/common.rst
docs/source/shellcraft/i386.rst
docs/source/shellcraft/mips.rst
docs/source/shellcraft/regsort.rst
docs/source/shellcraft/thumb.rst
docs/source/tubes/processes.rst
docs/source/tubes/serial.rst
docs/source/tubes/sockets.rst
docs/source/tubes/ssh.rst
docs/source/util/crc.rst
docs/source/util/cyclic.rst
docs/source/util/fiddling.rst
docs/source/util/hashes.rst
docs/source/util/iters.rst
docs/source/util/lists.rst
docs/source/util/misc.rst
docs/source/util/net.rst
docs/source/util/packing.rst
docs/source/util/proc.rst
docs/source/util/safeeval.rst
docs/source/util/sh_string.rst
docs/source/util/web.rst
examples/README.md
examples/android.py
examples/args.py
examples/asm.py
examples/attach.py
examples/clean_and_log.py
examples/gen-README.py
examples/indented.py
pwntools.egg-info/PKG-INFO
pwntools.egg-info/SOURCES.txt
pwntools.egg-info/dependency_links.txt
pwntools.egg-info/entry_points.txt
pwntools.egg-info/requires.txt
pwntools.egg-info/top_level.txt