Metadata-Version: 1.1
Name: pwntools
Version: 3.2.0
Summary: Pwntools CTF framework and exploit development library.
Home-page: https://pwntools.com
Author: Gallopsled et al.
Author-email: #pwntools @ freenode.net
License: Mostly MIT, some GPL/BSD, see LICENSE-pwntools.txt
Download-URL: https://github.com/Gallopsled/pwntools/releases
Keywords: pwntools exploit ctf capture the flag binary wargame overflow stack heap defcon
Platform: UNKNOWN
Classifier: Development Status :: 5 - Production/Stable
Classifier: Environment :: Console
Classifier: Intended Audience :: Developers
Classifier: Intended Audience :: Science/Research
Classifier: Intended Audience :: System Administrators
Classifier: License :: OSI Approved :: MIT License
Classifier: Natural Language :: English
Classifier: Operating System :: POSIX :: Linux
Classifier: Programming Language :: Python :: 2.7
Classifier: Topic :: Security
Classifier: Topic :: Software Development :: Assemblers
Classifier: Topic :: Software Development :: Debuggers
Classifier: Topic :: Software Development :: Disassemblers
Classifier: Topic :: Software Development :: Embedded Systems
Classifier: Topic :: Software Development :: Libraries :: Python Modules
Classifier: Topic :: System :: System Shells
Classifier: Topic :: Utilities
